divisible_by_3_or_not/__init__.py
divisible_by_3_or_not/check_divisable_by_3.py
divisible_by_3_turing_machine-1.0.0.dist-info/licenses/LICENSE
divisible_by_3_turing_machine-1.0.0.dist-info/METADATA
divisible_by_3_turing_machine-1.0.0.dist-info/WHEEL
divisible_by_3_turing_machine-1.0.0.dist-info/top_level.txt
divisible_by_3_turing_machine-1.0.0.dist-info/RECORD
