Metadata-Version: 2.4
Name: divisible_by_3_turing_machine
Version: 1.0.0
Summary: A simple Turing machine for checking binary divisibility by 3
Author: Mohamed Khaled
Author-email: Mohamed Khaled <mokhaled732003@gmail.com>
Requires-Python: >=3.6
License-File: LICENSE
Dynamic: author
Dynamic: license-file
Dynamic: requires-python
